git_whatsup/__init__.py
git_whatsup/__main__.py
git_whatsup/datastructures.py
git_whatsup/output.py
git_whatsup/preview.py
git_whatsup/version.py
git_whatsup/working_copy.py
git_whatsup-0.1.0.dist-info/DESCRIPTION.rst
git_whatsup-0.1.0.dist-info/LICENSE.txt
git_whatsup-0.1.0.dist-info/METADATA
git_whatsup-0.1.0.dist-info/RECORD
git_whatsup-0.1.0.dist-info/WHEEL
git_whatsup-0.1.0.dist-info/entry_points.txt
git_whatsup-0.1.0.dist-info/metadata.json
git_whatsup-0.1.0.dist-info/top_level.txt
