Metadata-Version: 2.0
Name: git-whatsup
Version: 0.1.0
Summary: Tool to list up remote branches that conflict with the current working copy.
Home-page: https://github.com/NoRedInk/git-whatsup
Author: Marica Odagaki
Author-email: marica@noredink.com
License: MIT
Keywords: git development
Platform: UNKNOWN
Classifier: Development Status :: 3 - Alpha
Classifier: Intended Audience :: Developers
Classifier: License :: OSI Approved :: MIT License
Classifier: Natural Language :: English
Classifier: Operating System :: POSIX
Classifier: Programming Language :: Python :: 3.5
Classifier: Programming Language :: Python :: 3.6
Classifier: Topic :: Software Development
Requires-Dist: pygit2
